django_execute_code/__init__.py
django_execute_code/apps.py
django_execute_code/forms.py
django_execute_code/urls.py
django_execute_code/views.py
django_execute_code/static/django_execute_code/css/styles.css
django_execute_code/static/django_execute_code/js/codestyle.js
django_execute_code/static/django_execute_code/js/jquery.js
django_execute_code/templates/django_execute_code/pre_output.html
django_execute_code/templates/django_execute_code/run_code.tpl.html
django_execute_code-0.4.dist-info/LICENCE.txt
django_execute_code-0.4.dist-info/METADATA
django_execute_code-0.4.dist-info/WHEEL
django_execute_code-0.4.dist-info/top_level.txt
django_execute_code-0.4.dist-info/RECORD
